IbmDeveloperworksQuanbuJiaochengSan/README.md
IbmDeveloperworksQuanbuJiaochengSan/__init__.py
IbmDeveloperworksQuanbuJiaochengSan/__main__.py
IbmDeveloperworksQuanbuJiaochengSan/file.epub
IbmDeveloperworksQuanbuJiaochengSan/index.html
IbmDeveloperworksQuanbuJiaochengSan/css/__init__.py
IbmDeveloperworksQuanbuJiaochengSan/css/annotations.css
IbmDeveloperworksQuanbuJiaochengSan/css/main.css
IbmDeveloperworksQuanbuJiaochengSan/css/normalize.css
IbmDeveloperworksQuanbuJiaochengSan/css/popup.css
IbmDeveloperworksQuanbuJiaochengSan/font/__init__.py
IbmDeveloperworksQuanbuJiaochengSan/font/fontello.eot
IbmDeveloperworksQuanbuJiaochengSan/font/fontello.svg
IbmDeveloperworksQuanbuJiaochengSan/font/fontello.ttf
IbmDeveloperworksQuanbuJiaochengSan/font/fontello.woff
IbmDeveloperworksQuanbuJiaochengSan/img/__init__.py
IbmDeveloperworksQuanbuJiaochengSan/img/annotator-glyph-sprite.png
IbmDeveloperworksQuanbuJiaochengSan/img/annotator-icon-sprite.png
IbmDeveloperworksQuanbuJiaochengSan/img/apple-touch-icon.png
IbmDeveloperworksQuanbuJiaochengSan/img/cancelfullscreen.png
IbmDeveloperworksQuanbuJiaochengSan/img/close.png
IbmDeveloperworksQuanbuJiaochengSan/img/fullscreen.png
IbmDeveloperworksQuanbuJiaochengSan/img/loader.gif
IbmDeveloperworksQuanbuJiaochengSan/img/menu-icon.png
IbmDeveloperworksQuanbuJiaochengSan/img/save.png
IbmDeveloperworksQuanbuJiaochengSan/img/saved.png
IbmDeveloperworksQuanbuJiaochengSan/img/settings-s.png
IbmDeveloperworksQuanbuJiaochengSan/img/settings.png
IbmDeveloperworksQuanbuJiaochengSan/img/star.png
IbmDeveloperworksQuanbuJiaochengSan/js/__init__.py
IbmDeveloperworksQuanbuJiaochengSan/js/epub.js
IbmDeveloperworksQuanbuJiaochengSan/js/epub.min.js
IbmDeveloperworksQuanbuJiaochengSan/js/epub.min.map
IbmDeveloperworksQuanbuJiaochengSan/js/hooks.min.js
IbmDeveloperworksQuanbuJiaochengSan/js/hooks.min.map
IbmDeveloperworksQuanbuJiaochengSan/js/reader.js
IbmDeveloperworksQuanbuJiaochengSan/js/reader.js.map
IbmDeveloperworksQuanbuJiaochengSan/js/reader.min.js
ibm_developerworks_quanbu_jiaocheng_san-2024.3.5.0.dist-info/METADATA
ibm_developerworks_quanbu_jiaocheng_san-2024.3.5.0.dist-info/WHEEL
ibm_developerworks_quanbu_jiaocheng_san-2024.3.5.0.dist-info/entry_points.txt
ibm_developerworks_quanbu_jiaocheng_san-2024.3.5.0.dist-info/top_level.txt
ibm_developerworks_quanbu_jiaocheng_san-2024.3.5.0.dist-info/RECORD
